prestashop_orders_client/__init__.py
prestashop_orders_client/client.py
prestashop_orders_client/exceptions.py
prestashop_orders_client/parser.py
prestashop_orders_client/utils.py
prestashop_orders_client-1.0.0.dist-info/LICENSE
prestashop_orders_client-1.0.0.dist-info/METADATA
prestashop_orders_client-1.0.0.dist-info/WHEEL
prestashop_orders_client-1.0.0.dist-info/top_level.txt
prestashop_orders_client-1.0.0.dist-info/RECORD
