Metadata-Version: 2.1
Name: prestashop-orders-client
Version: 1.0.0
Summary: A simple Python client for PrestaShop API to extract orders
Home-page: https://github.com/vernon-gant/prestashop_orders_client
Author: Aleksandr Zakharov
Author-email: Aleksandr Zakharov <aleksza.4119@gmail.com>
License: Apache License 2.0
Project-URL: homepage, https://github.com/vernon-gant/prestashop_orders_client
Project-URL: bug-tracker, https://github.com/vernon-gant/prestashop_orders_client/issues
Project-URL: source, https://github.com/vernon-gant/prestashop_orders_client
Keywords: prestashop orders api client
Classifier: Intended Audience :: Developers
Classifier: License :: OSI Approved :: Apache Software License
Classifier: Programming Language :: Python :: 3.10
Classifier: Topic :: Software Development :: Libraries
Requires-Python: >=3.10
License-File: LICENSE
Requires-Dist: requests (>=2.28.1)
Requires-Dist: xmltodict (>=0.13.0)
